AqDsKit/__init__.py
AqDsKit/accessors/__init__.py
AqDsKit/accessors/db/__init__.py
AqDsKit/accessors/db/dbapi.py
AqDsKit/accessors/db/dbconfigs.py
AqDsKit/accessors/db/drivers.py
AqDsKit/accessors/db/hadoopconfigs.py
AqDsKit/accessors/fs/__init__.py
AqDsKit/accessors/fs/file_loaders.py
AqDsKit/accessors/fs/remote.py
AqDsKit/accessors/fs/s3.py
AqDsKit/accessors/fs/spark.py
AqDsKit/metrics/__init__.py
AqDsKit/metrics/sklearn/__init__.py
AqDsKit/metrics/sklearn/custom_scorer.py
AqDsKit/metrics/sklearn/custom_scoring.py
AqDsKit/models/__init__.py
AqDsKit/models/Explore/__init__.py
AqDsKit/models/Explore/preview.py
AqDsKit/models/FeatureEngineer/__init__.py
AqDsKit/models/FeatureEngineer/featureHelper.py
AqDsKit/models/FeatureEngineer/transformers.py
AqDsKit/models/evaluation/__init__.py
AqDsKit/models/evaluation/validation.py
AqDsKit/models/sklearn/__init__.py
AqDsKit/models/sklearn/custom_cluster.py
AqDsKit/models/sklearn/general.py
AqDsKit/models/sklearn/hyperparam.py
AqDsKit/models/sklearn/ordinal_clf.py
AqDsKit/models/statmodels/__init__.py
AqDsKit/models/statmodels/linear_model.py
AqDsKit/models/utils/__init__.py
AqDsKit/models/utils/checks.py
AqDsKit/models/utils/parallel.py
AqDsKit/models/utils/support.py
AqDsKit/plots/__init__.py
AqDsKit/plots/commons/__init__.py
AqDsKit/plots/commons/basics.py
AqDsKit/plots/commons/tools.py
AqDsKit/plots/sklearn/__init__.py
AqDsKit/plots/sklearn/clustering.py
AqDsKit/plots/sklearn/general.py
AqDsKit/utils/__init__.py
AqDsKit/utils/custom_structures.py
AqDsKit/utils/parallel.py
AqDsKit-0.0.3.dist-info/LICENSE
AqDsKit-0.0.3.dist-info/METADATA
AqDsKit-0.0.3.dist-info/WHEEL
AqDsKit-0.0.3.dist-info/top_level.txt
AqDsKit-0.0.3.dist-info/RECORD
