Metadata-Version: 2.1
Name: AqDsKit
Version: 0.0.3
Summary: Data Scientist Toolkits
Home-page: https://github.com/luntaixiax/aq-dskit
Author: luntaixiax
Author-email: ailunqian124@gmail.com
Classifier: Programming Language :: Python :: 3
Classifier: License :: OSI Approved :: MIT License
Classifier: Operating System :: OS Independent
Requires-Python: >=3.6
License-File: LICENSE
